LaudaDriver/__init__.py
LaudaDriver/lauda.py
LaudaDriver-1.0.0a7.dist-info/DESCRIPTION.rst
LaudaDriver-1.0.0a7.dist-info/METADATA
LaudaDriver-1.0.0a7.dist-info/RECORD
LaudaDriver-1.0.0a7.dist-info/WHEEL
LaudaDriver-1.0.0a7.dist-info/metadata.json
LaudaDriver-1.0.0a7.dist-info/top_level.txt
